{
  "_meta": {
    "version": "1.0.0",
    "description": "Universal domain definitions for aOa semantic tagging. Seeded on quickstart for instant coverage across all codebases.",
    "updated": "2026-01-14"
  },
  "domains": [
    {
      "name": "@authentication",
      "description": "User identity verification, login/logout, session management",
      "confidence": 0.9,
      "terms": ["auth", "login", "logout", "signin", "signout", "authenticate", "credential", "password", "token", "jwt", "oauth", "session", "identity", "principal", "user_auth", "verify_user", "check_auth"]
    },
    {
      "name": "@authorization",
      "description": "Access control, permissions, roles, policies",
      "confidence": 0.9,
      "terms": ["authorize", "permission", "role", "access_control", "acl", "rbac", "policy", "grant", "deny", "allowed", "forbidden", "can_access", "has_permission", "check_permission", "require_role"]
    },
    {
      "name": "@database",
      "description": "Data persistence, queries, ORM, migrations",
      "confidence": 0.9,
      "terms": ["database", "query", "sql", "orm", "model", "schema", "migration", "repository", "entity", "record", "table", "column", "index", "transaction", "commit", "rollback", "cursor", "connection_pool"]
    },
    {
      "name": "@api",
      "description": "HTTP endpoints, REST, GraphQL, request handling",
      "confidence": 0.9,
      "terms": ["api", "endpoint", "route", "handler", "controller", "request", "response", "rest", "graphql", "http", "get", "post", "put", "delete", "patch", "middleware", "router"]
    },
    {
      "name": "@testing",
      "description": "Unit tests, integration tests, mocks, assertions",
      "confidence": 0.9,
      "terms": ["test", "spec", "describe", "expect", "assert", "mock", "stub", "spy", "fixture", "setup", "teardown", "beforeEach", "afterEach", "it", "should", "verify", "unittest", "pytest", "jest"]
    },
    {
      "name": "@configuration",
      "description": "App settings, environment variables, feature flags",
      "confidence": 0.85,
      "terms": ["config", "settings", "env", "environment", "option", "preference", "feature_flag", "toggle", "constant", "default", "override", "load_config", "get_setting", "dotenv"]
    },
    {
      "name": "@logging",
      "description": "Log output, debugging, tracing, monitoring",
      "confidence": 0.85,
      "terms": ["log", "logger", "debug", "info", "warn", "error", "trace", "print", "console", "stdout", "stderr", "level", "format", "handler", "appender", "syslog"]
    },
    {
      "name": "@error_handling",
      "description": "Exceptions, error recovery, fault tolerance",
      "confidence": 0.9,
      "terms": ["error", "exception", "throw", "catch", "try", "finally", "raise", "handle", "recover", "fallback", "retry", "circuit_breaker", "error_handler", "on_error", "fail", "panic"]
    },
    {
      "name": "@caching",
      "description": "In-memory cache, distributed cache, memoization",
      "confidence": 0.85,
      "terms": ["cache", "cached", "memoize", "redis", "memcached", "lru", "ttl", "expire", "invalidate", "refresh", "hit", "miss", "store", "retrieve", "warm", "cold"]
    },
    {
      "name": "@validation",
      "description": "Input validation, sanitization, schema enforcement",
      "confidence": 0.85,
      "terms": ["validate", "validator", "sanitize", "schema", "check", "verify", "constraint", "rule", "required", "optional", "pattern", "format", "type_check", "bounds", "range"]
    },
    {
      "name": "@serialization",
      "description": "JSON, XML, protobuf, data encoding/decoding",
      "confidence": 0.85,
      "terms": ["serialize", "deserialize", "json", "xml", "yaml", "protobuf", "marshal", "unmarshal", "encode", "decode", "parse", "stringify", "dump", "load", "to_dict", "from_dict"]
    },
    {
      "name": "@security",
      "description": "Encryption, hashing, secrets, vulnerability prevention",
      "confidence": 0.9,
      "terms": ["encrypt", "decrypt", "hash", "salt", "secret", "secure", "crypto", "cipher", "key", "sign", "verify", "hmac", "aes", "rsa", "certificate", "ssl", "tls", "sanitize", "escape"]
    },
    {
      "name": "@concurrency",
      "description": "Threads, async, locks, parallel processing",
      "confidence": 0.85,
      "terms": ["async", "await", "thread", "process", "parallel", "concurrent", "lock", "mutex", "semaphore", "queue", "worker", "pool", "spawn", "join", "atomic", "synchronize", "future", "promise"]
    },
    {
      "name": "@events",
      "description": "Event emitters, pub/sub, message queues, webhooks",
      "confidence": 0.85,
      "terms": ["event", "emit", "listen", "subscribe", "publish", "dispatch", "handler", "callback", "hook", "trigger", "observer", "listener", "message", "queue", "topic", "channel", "webhook"]
    },
    {
      "name": "@file_io",
      "description": "File reading, writing, streaming, paths",
      "confidence": 0.85,
      "terms": ["file", "read", "write", "open", "close", "stream", "buffer", "path", "directory", "folder", "exists", "create", "delete", "move", "copy", "rename", "stat", "glob"]
    },
    {
      "name": "@networking",
      "description": "HTTP clients, sockets, DNS, protocols",
      "confidence": 0.85,
      "terms": ["http", "https", "socket", "tcp", "udp", "dns", "url", "uri", "fetch", "request", "client", "connection", "timeout", "retry", "proxy", "host", "port", "header"]
    },
    {
      "name": "@cli",
      "description": "Command-line interfaces, argument parsing, terminal",
      "confidence": 0.85,
      "terms": ["cli", "command", "arg", "argv", "flag", "option", "parse", "terminal", "console", "stdin", "stdout", "prompt", "input", "output", "shell", "exec", "spawn", "subprocess"]
    },
    {
      "name": "@ui",
      "description": "User interface, components, rendering, state",
      "confidence": 0.85,
      "terms": ["component", "render", "view", "template", "layout", "style", "css", "dom", "element", "widget", "button", "form", "input", "modal", "dialog", "menu", "navigation", "theme"]
    },
    {
      "name": "@state",
      "description": "State management, stores, reducers, reactivity",
      "confidence": 0.85,
      "terms": ["state", "store", "reducer", "action", "dispatch", "selector", "subscribe", "reactive", "observable", "computed", "watch", "effect", "atom", "signal", "context", "provider"]
    },
    {
      "name": "@data_transform",
      "description": "Data mapping, filtering, aggregation, pipelines",
      "confidence": 0.8,
      "terms": ["map", "filter", "reduce", "transform", "convert", "aggregate", "group", "sort", "merge", "flatten", "normalize", "denormalize", "pipeline", "chain", "compose"]
    },
    {
      "name": "@scheduling",
      "description": "Cron jobs, task scheduling, timers, intervals",
      "confidence": 0.8,
      "terms": ["schedule", "cron", "job", "task", "timer", "interval", "delay", "timeout", "recurring", "periodic", "once", "at", "every", "run_at", "schedule_task", "background"]
    },
    {
      "name": "@monitoring",
      "description": "Metrics, health checks, alerting, observability",
      "confidence": 0.8,
      "terms": ["metric", "monitor", "health", "check", "alert", "trace", "span", "telemetry", "prometheus", "grafana", "dashboard", "counter", "gauge", "histogram", "latency", "throughput"]
    },
    {
      "name": "@deployment",
      "description": "CI/CD, containers, infrastructure, releases",
      "confidence": 0.8,
      "terms": ["deploy", "release", "build", "ci", "cd", "pipeline", "docker", "container", "kubernetes", "helm", "terraform", "ansible", "artifact", "package", "publish", "rollout", "rollback"]
    },
    {
      "name": "@search",
      "description": "Full-text search, indexing, ranking, queries",
      "confidence": 0.8,
      "terms": ["search", "index", "query", "filter", "rank", "score", "match", "fuzzy", "autocomplete", "suggest", "highlight", "facet", "elasticsearch", "solr", "lucene", "inverted"]
    },
    {
      "name": "@analytics",
      "description": "Usage tracking, metrics collection, reporting",
      "confidence": 0.8,
      "terms": ["analytics", "track", "event", "metric", "report", "dashboard", "funnel", "cohort", "segment", "conversion", "retention", "engagement", "pageview", "session", "user_id"]
    },
    {
      "name": "@notification",
      "description": "Push notifications, email, SMS, alerts",
      "confidence": 0.8,
      "terms": ["notification", "notify", "alert", "email", "sms", "push", "send", "broadcast", "template", "recipient", "subscribe", "unsubscribe", "preference", "channel", "delivery"]
    },
    {
      "name": "@payment",
      "description": "Transactions, billing, subscriptions, refunds",
      "confidence": 0.8,
      "terms": ["payment", "pay", "charge", "refund", "subscription", "billing", "invoice", "transaction", "checkout", "cart", "order", "price", "discount", "coupon", "stripe", "paypal"]
    },
    {
      "name": "@media",
      "description": "Images, video, audio, file uploads",
      "confidence": 0.8,
      "terms": ["image", "video", "audio", "media", "upload", "download", "resize", "compress", "thumbnail", "encode", "decode", "stream", "player", "recorder", "cdn", "storage"]
    },
    {
      "name": "@localization",
      "description": "i18n, translations, locale, formatting",
      "confidence": 0.8,
      "terms": ["i18n", "l10n", "locale", "translate", "translation", "language", "format", "currency", "date_format", "number_format", "rtl", "ltr", "plural", "interpolate", "message"]
    },
    {
      "name": "@rate_limiting",
      "description": "Throttling, quotas, abuse prevention",
      "confidence": 0.8,
      "terms": ["rate_limit", "throttle", "quota", "limit", "cooldown", "backoff", "retry_after", "bucket", "window", "requests_per", "too_many", "abuse", "spam", "flood"]
    },
    {
      "name": "@feature_flags",
      "description": "Feature toggles, A/B testing, rollouts",
      "confidence": 0.8,
      "terms": ["feature_flag", "toggle", "flag", "variant", "experiment", "ab_test", "rollout", "canary", "percentage", "enabled", "disabled", "override", "segment", "targeting"]
    },
    {
      "name": "@migrations",
      "description": "Database migrations, schema changes, versioning",
      "confidence": 0.8,
      "terms": ["migration", "migrate", "upgrade", "downgrade", "version", "revision", "alter", "create_table", "drop_table", "add_column", "remove_column", "seed", "rollback"]
    }
  ]
}
